Metadata-Version: 2.1
Name: nbinspector
Version: 0.1
Summary: Tool to help inspect arbitrary objects in Jupyter notebooks
Home-page: https://github.com/mwharton3/nbinspector
Download-URL: https://github.com/mwharton3/nbinspector/archive/0.1.tar.gz
Author: Michael Wharton
Author-email: mwharton3@protonmail.com
Classifier: Development Status :: 4 - Beta
Classifier: Intended Audience :: Developers
Classifier: Topic :: Software Development :: Libraries
Classifier: License :: OSI Approved :: MIT License
Classifier: Programming Language :: Python :: 3.6
Classifier: Programming Language :: Python :: 3.7
Classifier: Programming Language :: Python :: 3.8
Classifier: Programming Language :: Python :: 3.9
License-File: LICENSE
